<?xml version="1.0" encoding="utf-8"?>
<language>
  <definitions>
    <definition>
      <key>box_manufacturer_info_heading</key>
      <value><![CDATA[Tillverkarinfo]]></value>
      <group>modules-boxes</group>
    </definition>
    <definition>
      <key>box_manufacturer_info_website</key>
      <value><![CDATA[Besök %s's websida]]></value>
      <group>modules-boxes</group>
    </definition>
    <definition>
      <key>box_manufacturer_info_products</key>
      <value><![CDATA[Visa andra produkter]]></value>
      <group>modules-boxes</group>
    </definition>
  </definitions>
</language>